venv_clean/__init__.py
venv_clean/__main__.py
venv_clean/core/__init__.py
venv_clean/core/utils.py
venv_clean/core/ui/__init__.py
venv_clean/core/ui/manage.py
venv_clean/core/ui/venvview.py
venv_clean-0.1.0.dist-info/LICENSE
venv_clean-0.1.0.dist-info/METADATA
venv_clean-0.1.0.dist-info/WHEEL
venv_clean-0.1.0.dist-info/entry_points.txt
venv_clean-0.1.0.dist-info/top_level.txt
venv_clean-0.1.0.dist-info/RECORD
