Metadata-Version: 2.1
Name: venv-clean
Version: 0.1.0
Summary: Finds python virtual environments in your machine. Displays disk usage and other data, and allows you to delete them.
Home-page: https://github.com/jcapona/venv-clean
Author: Jorge Capona
Author-email: jcapona@gmail.com
License: MIT
Keywords: python venv virtual environment env manage
Platform: UNKNOWN
Classifier: Development Status :: 3 - Alpha
Classifier: Intended Audience :: Developers
Classifier: Topic :: Software Development
Classifier: Topic :: Software Development :: Embedded Systems
Classifier: Topic :: System
Classifier: License :: OSI Approved :: MIT License
Classifier: Programming Language :: Python :: 3.6
Requires-Dist: asciimatics (<2,>=1.10.0)
